easyfilewatcher/EasyFileWatcher.py
easyfilewatcher/UoW.py
easyfilewatcher/__init__.py
easyfilewatcher/adapters/ORM.py
easyfilewatcher/adapters/Repository.py
easyfilewatcher/adapters/__init__.py
easyfilewatcher/domain/EasyFileWatcherUnit.py
easyfilewatcher/domain/__init__.py
easyfilewatcher/utils/__init__.py
easyfilewatcher/utils/config.py
EasyFileWatcher-0.0.5.dist-info/LICENSE
EasyFileWatcher-0.0.5.dist-info/METADATA
EasyFileWatcher-0.0.5.dist-info/WHEEL
EasyFileWatcher-0.0.5.dist-info/top_level.txt
EasyFileWatcher-0.0.5.dist-info/RECORD
