Metadata-Version: 2.1
Name: EasyFileWatcher
Version: 0.0.5
Summary: This is yet another FileWatcher. Developed to run smoothier, without sideffects and give more control to the developer in comparison to common packages for such purpose
Home-page: https://github.com/efstratios97/EasyFileWatcher
Author: Efstratios Pahis
License: MIT
Classifier: Programming Language :: Python :: 3
Classifier: License :: OSI Approved :: MIT License
Classifier: Operating System :: OS Independent
Requires-Python: >=3.8
License-File: LICENSE
Requires-Dist: apscheduler
Requires-Dist: SQLAlchemy
Requires-Dist: SQLAlchemy-Utils
